.gitignore
CHANGES.txt
MANIFEST.in
Makefile
README.rst
bootstrap.py
buildout.cfg
setup.py
docs/conf.py
docs/index.rst
docs/requirements.txt
src/WAVELibrary/__init__.py
src/WAVELibrary/keywords.robot
src/WAVELibrary/profile/extensions/wavetoolbar-robot@plone.org.xpi
src/WAVELibrary/profile/extensions/wavetoolbar@webaim.org.xpi
src/robotframework_wavelibrary.egg-info/PKG-INFO
src/robotframework_wavelibrary.egg-info/SOURCES.txt
src/robotframework_wavelibrary.egg-info/dependency_links.txt
src/robotframework_wavelibrary.egg-info/not-zip-safe
src/robotframework_wavelibrary.egg-info/requires.txt
src/robotframework_wavelibrary.egg-info/top_level.txt
wavetoolbar-robot/chrome.manifest
wavetoolbar-robot/install.rdf
wavetoolbar-robot/chrome/content/wavetoolbar-robot.js
wavetoolbar-robot/chrome/content/wavetoolbar-robot.xul