Metadata-Version: 1.0
Name: robotframework-wavelibrary
Version: 0.1.2
Summary: Robot Framework resources for automating WebAIM Wave Toolbar
Home-page: https://github.com/datakurre/robotframework-wavelibrary/
Author: Asko Soukka
Author-email: asko.soukka@iki.fi
License: GPL
Platform: UNKNOWN
Classifier: Programming Language :: Python
